[
  {
    "title": "Automagic Websites",
    "link": "https://github.com/jere-mie/automagic-websites",
    "points": [
      {
        "text": "Full stack web app featuring <b>user authentication</b>"
      },
      {
        "text": "Allows users to create, host, and export their own simple website"
      },
      {
        "text": "Created using <b>Python, Flask, SQLAlchemy, Bootstrap</b>"
      }
    ]
  },
  {
    "title": "Easy-MASM",
    "link": "https://github.com/jere-mie/easy-masm",
    "points": [
      {
        "text": "Automated system for assembling, linking, and executing <b>MASM32</b> programs"
      },
      {
        "text": "Used by over <b>200 students</b>"
      },
      {
        "text": "Created using <b>bash and batch</b>"
      }
    ]
  },
  {
    "title": "UWindsor API",
    "link": "https://github.com/jere-mie/uwindsor-api",
    "points": [
      {
        "text": "<b>REST API</b> created to serve data related to the University of Windsor"
      },
      {
        "text": "Serves course, staff and building data"
      },
      {
        "text": "Created using <b>Golang, Gin, and SQLX</b>"
      }
    ]
  },
  {
    "title": "UWindsor Discord Authentication",
    "link": "https://github.com/jere-mie/uwin-discord-auth",
    "points": [
      {
        "text": "Web interface to authenticate UWindsor students and add them to a Discord server"
      },
      {
        "text": "Uses <b>OAuth2</b> to prevent professors, staff, and non-students from joining"
      },
      {
        "text": "Created using <b>Python, Flask, SQLAlchemy, and OAuth2</b>"
      }
    ]
  }
]
